README.md
jupyjet.py
setup.py
jupyjet.egg-info/PKG-INFO
jupyjet.egg-info/SOURCES.txt
jupyjet.egg-info/dependency_links.txt
jupyjet.egg-info/requires.txt
jupyjet.egg-info/top_level.txt