Metadata-Version: 1.0
Name: jupyjet
Version: 0.3.0
Summary: jupyter extention to generate python modules
Home-page: https://github.com/pelodelfuego/jupyjet
Author: Clément CREPY
Author-email: clement.crepy@gmail.com
License: MIT
Keywords: jupyter,notebook,module,jupyjet
Platform: UNKNOWN
